texture2ddecoder/_texture2ddecoder.pyi
texture2ddecoder/__init__.py
texture2ddecoder/_texture2ddecoder.pypy310-pp73-darwin.so
texture2ddecoder/py.typed
texture2ddecoder-1.0.5.dist-info/RECORD
texture2ddecoder-1.0.5.dist-info/LICENSE
texture2ddecoder-1.0.5.dist-info/WHEEL
texture2ddecoder-1.0.5.dist-info/top_level.txt
texture2ddecoder-1.0.5.dist-info/METADATA
