Metadata-Version: 2.1
Name: texture2ddecoder
Version: 1.0.5
Summary: a python wrapper for Perfare's Texture2DDecoder
Author-email: Rudolf Kolbe <rkolbe96@gmail.com>
License: MIT License
Project-URL: Homepage, https://github.com/K0lb3/texture2ddecoder
Project-URL: Bug Tracker, https://github.com/K0lb3/texture2ddecoder/issues
Keywords: astc,texture
Classifier: License :: OSI Approved :: MIT License
Classifier: Operating System :: OS Independent
Classifier: Intended Audience :: Developers
Classifier: Programming Language :: Python
Classifier: Programming Language :: Python :: 3
Classifier: Programming Language :: Python :: 3.7
Classifier: Programming Language :: Python :: 3.8
Classifier: Programming Language :: Python :: 3.9
Classifier: Programming Language :: Python :: 3.10
Classifier: Programming Language :: Python :: 3.11
Classifier: Programming Language :: Python :: 3.12
Classifier: Programming Language :: Python :: 3.13
Classifier: Topic :: Multimedia :: Graphics
Classifier: Topic :: Software Development :: Libraries :: Python Modules
Requires-Python: >=3.7
License-File: LICENSE
Provides-Extra: tests
Requires-Dist: pytest>=8.3.3; extra == "tests"
Requires-Dist: pillow>=10.4.0; extra == "tests"
